serasa_sdk/__init__.py
serasa_sdk/client.py
serasa_sdk/enums.py
serasa_sdk/exceptions.py
serasa_sdk/routes.py
serasa_sdk-0.1.6.dist-info/METADATA
serasa_sdk-0.1.6.dist-info/WHEEL
serasa_sdk-0.1.6.dist-info/RECORD
